README.md
setup.py
tsru/__init__.py
tsru.egg-info/PKG-INFO
tsru.egg-info/SOURCES.txt
tsru.egg-info/dependency_links.txt
tsru.egg-info/top_level.txt
tsru/printing/LoadingSpinner.py
tsru/printing/__init__.py