Metadata-Version: 2.1
Name: tsru
Version: 0.1.0
Summary: A simple library for various miscellaneous things
Home-page: https://github.com/GaviTSRA/tsru
Author: GaviTSRA
Author-email: gavitsra@gmail.com
License: UNKNOWN
Platform: UNKNOWN
